identidad_ec/__init__.py
identidad_ec/cedula.py
identidad_ec/ruc.py
identidad_ec/utils.py
identidad_ec/validar_cli.py
identidad_ec-0.1.3.dist-info/METADATA
identidad_ec-0.1.3.dist-info/WHEEL
identidad_ec-0.1.3.dist-info/entry_points.txt
identidad_ec-0.1.3.dist-info/top_level.txt
identidad_ec-0.1.3.dist-info/RECORD
