Metadata-Version: 2.4
Name: identidad-ec
Version: 0.1.3
Summary: Validador de Cédula y RUC del Ecuador
Author-email: Rudy Estefang Zambrano Infante <estefang@zamintech.net>
Keywords: ecuador,cedula,ruc,validacion,identidad
Classifier: Programming Language :: Python :: 3
Classifier: License :: OSI Approved :: MIT License
Classifier: Operating System :: OS Independent
Classifier: Topic :: Software Development :: Libraries
Classifier: Intended Audience :: Developers
Requires-Python: >=3.8
